cisne/__init__.py
cisne/core.py
cisne-0.0.0.dist-info/licenses/LICENSE
cisne-0.0.0.dist-info/METADATA
cisne-0.0.0.dist-info/WHEEL
cisne-0.0.0.dist-info/top_level.txt
cisne-0.0.0.dist-info/RECORD
